godice/__init__.py
godice/demo.py
godice/dice.py
godice/factory.py
godice/xyzinterpret.py
godice-0.1.2.dist-info/LICENSE.md
godice-0.1.2.dist-info/WHEEL
godice-0.1.2.dist-info/METADATA
godice-0.1.2.dist-info/RECORD
