Metadata-Version: 2.1
Name: godice
Version: 0.1.2
Summary: A Python API for GoDice
Author-email: Guy Levi <guyguylevi60@gmail.com>, Anton Ptashnik <iavtomator@gmail.com>
Requires-Python: >=3.6
Classifier: Framework :: AsyncIO
Classifier: Operating System :: Microsoft :: Windows :: Windows 10
Classifier: Operating System :: POSIX :: Linux
Classifier: Operating System :: MacOS
Requires-Dist: bleak >=0.20.2
Project-URL: Home, https://github.com/ParticulaCode/GoDicePythonAPI
